inferaSDK/__init__.py
inferaSDK/client.py
inferasdk-0.1.2.dist-info/METADATA
inferasdk-0.1.2.dist-info/WHEEL
inferasdk-0.1.2.dist-info/RECORD
