Metadata-Version: 2.3
Name: InferaSDK
Version: 0.1.2
Summary: A Python SDK for the Infera API
Project-URL: Homepage, https://infera.org
Project-URL: Repository, https://github.com/inferanetwork
Author-email: white <white@infera.org>
License: MIT
Classifier: License :: OSI Approved :: MIT License
Classifier: Operating System :: OS Independent
Classifier: Programming Language :: Python :: 3
Requires-Python: >=3.7
Requires-Dist: aiohttp>=3.7.0
Requires-Dist: asyncio
